perde_msgpack-0.0.1.dist-info/METADATA
perde_msgpack-0.0.1.dist-info/WHEEL
perde_msgpack.cpython-38-x86_64-linux-gnu.so
perde_msgpack-0.0.1.dist-info/RECORD
