Metadata-Version: 2.1
Name: perde-msgpack
Version: 0.0.1
Classifier: Development Status :: 3 - Alpha
Classifier: Intended Audience :: Developers
Classifier: License :: OSI Approved :: MIT License
Classifier: Operating System :: MacOS
Classifier: Operating System :: Microsoft :: Windows
Classifier: Operating System :: POSIX :: Linux
Classifier: Programming Language :: Python :: 3
Classifier: Programming Language :: Python :: 3.7
Classifier: Programming Language :: Python :: 3.8
Classifier: Programming Language :: Python :: 3.9
Classifier: Programming Language :: Python
Classifier: Programming Language :: Rust
Classifier: Typing :: Typed
Summary: Fast and flexible MessagePack serialization library based on perde.
Keywords: dataclass dataclasses serialization serde
Home-Page: https://github.com/yushiomote/perde
Author: Yushi Omote <yushiomote@gmail.com>
Author-Email: Yushi Omote <yushiomote@gmail.com>
License: MIT
Requires-Python: >=3.7
